timesup/__about__.py
timesup/__init__.py
timesup-0.0.0.dist-info/METADATA
timesup-0.0.0.dist-info/WHEEL
timesup-0.0.0.dist-info/RECORD
